Metadata-Version: 1.1
Name: qnap-qsw
Version: 0.0.4
Summary: QNAP QSW API library
Home-page: https://github.com/Noltari/python-qnap-qsw
Author: noltari
Author-email: noltari@gmail.com
License: GPL2
Keywords: qnap,qsw,switch
Platform: any
Classifier: Development Status :: 2 - Pre-Alpha
Classifier: Topic :: Home Automation
Classifier: Intended Audience :: Developers
Classifier: License :: OSI Approved :: GNU General Public License v2 (GPLv2)
Classifier: Natural Language :: English
Classifier: Programming Language :: Python :: 3
Classifier: Programming Language :: Python :: 3.9
